<?xml version="1.0" encoding="UTF-8"?>
<document xmlns="http://v8.1c.ru/8.2/data/spreadsheet" xmlns:style="http://v8.1c.ru/8.1/data/ui/style" xmlns:v8="http://v8.1c.ru/8.1/data/core" xmlns:v8ui="http://v8.1c.ru/8.1/data/ui" xmlns:xs="http://www.w3.org/2001/XMLSchema" xmlns:xsi="http://www.w3.org/2001/XMLSchema-instance">
	<languageSettings>
		<currentLanguage>ru</currentLanguage>
		<defaultLanguage>ru</defaultLanguage>
		<languageInfo>
			<id>ru</id>
			<code>Русский</code>
			<description>Русский</description>
		</languageInfo>
	</languageSettings>
	<columns>
		<size>6</size>
		<columnsItem>
			<index>0</index>
			<column>
				<formatIndex>1</formatIndex>
			</column>
		</columnsItem>
		<columnsItem>
			<index>1</index>
			<column>
				<formatIndex>2</formatIndex>
			</column>
		</columnsItem>
		<columnsItem>
			<index>2</index>
			<column>
				<formatIndex>3</formatIndex>
			</column>
		</columnsItem>
		<columnsItem>
			<index>5</index>
			<column>
				<formatIndex>4</formatIndex>
			</column>
		</columnsItem>
	</columns>
	<rowsItem>
		<index>0</index>
		<row>
			<c>
				<c>
					<f>5</f>
				</c>
			</c>
			<c>
				<c>
					<f>6</f>
				</c>
			</c>
			<c>
				<c>
					<f>6</f>
				</c>
			</c>
			<c>
				<c>
					<f>6</f>
				</c>
			</c>
			<c>
				<c>
					<f>6</f>
				</c>
			</c>
			<c>
				<c>
					<f>7</f>
				</c>
			</c>
		</row>
	</rowsItem>
	<rowsItem>
		<index>1</index>
		<row>
			<c>
				<c>
					<f>8</f>
				</c>
			</c>
			<c>
				<c>
					<f>9</f>
					<tl>
						<v8:item>
							<v8:lang>ru</v8:lang>
							<v8:content>Наименование:</v8:content>
						</v8:item>
					</tl>
				</c>
			</c>
			<c>
				<c>
					<f>10</f>
					<parameter>Наименование</parameter>
				</c>
			</c>
			<c>
				<c>
					<f>0</f>
				</c>
			</c>
			<c>
				<c>
					<f>0</f>
				</c>
			</c>
			<c>
				<c>
					<f>11</f>
				</c>
			</c>
		</row>
	</rowsItem>
	<rowsItem>
		<index>2</index>
		<row>
			<c>
				<c>
					<f>8</f>
				</c>
			</c>
			<c>
				<c>
					<f>12</f>
					<tl>
						<v8:item>
							<v8:lang>ru</v8:lang>
							<v8:content>Количество:</v8:content>
						</v8:item>
					</tl>
				</c>
			</c>
			<c>
				<c>
					<f>13</f>
					<parameter>Количество</parameter>
				</c>
			</c>
			<c>
				<c>
					<f>0</f>
				</c>
			</c>
			<c>
				<c>
					<f>0</f>
				</c>
			</c>
			<c>
				<c>
					<f>11</f>
				</c>
			</c>
		</row>
	</rowsItem>
	<rowsItem>
		<index>3</index>
		<row>
			<c>
				<c>
					<f>8</f>
				</c>
			</c>
			<c>
				<c>
					<f>14</f>
					<tl>
						<v8:item>
							<v8:lang>ru</v8:lang>
							<v8:content>Дата производства:</v8:content>
						</v8:item>
					</tl>
				</c>
			</c>
			<c>
				<c>
					<f>15</f>
					<parameter>ДатаПроизводства</parameter>
				</c>
			</c>
			<c>
				<c>
					<f>0</f>
				</c>
			</c>
			<c>
				<c>
					<f>0</f>
				</c>
			</c>
			<c>
				<c>
					<f>11</f>
				</c>
			</c>
		</row>
	</rowsItem>
	<rowsItem>
		<index>4</index>
		<row>
			<c>
				<c>
					<f>8</f>
				</c>
			</c>
			<c>
				<c>
					<f>14</f>
					<tl>
						<v8:item>
							<v8:lang>ru</v8:lang>
							<v8:content>Срок годности:</v8:content>
						</v8:item>
					</tl>
				</c>
			</c>
			<c>
				<c>
					<f>15</f>
					<parameter>СрокГодности</parameter>
				</c>
			</c>
			<c>
				<c>
					<f>0</f>
				</c>
			</c>
			<c>
				<c>
					<f>0</f>
				</c>
			</c>
			<c>
				<c>
					<f>11</f>
				</c>
			</c>
		</row>
	</rowsItem>
	<rowsItem>
		<index>5</index>
		<row>
			<c>
				<c>
					<f>8</f>
				</c>
			</c>
			<c>
				<c>
					<f>16</f>
					<tl>
						<v8:item>
							<v8:lang>ru</v8:lang>
							<v8:content>Идентификатор ВСД</v8:content>
						</v8:item>
					</tl>
				</c>
			</c>
			<c>
				<c>
					<f>17</f>
					<parameter>ИдентификаторВСД</parameter>
				</c>
			</c>
			<c>
				<c>
					<f>0</f>
				</c>
			</c>
			<c>
				<c>
					<f>0</f>
				</c>
			</c>
			<c>
				<c>
					<f>11</f>
				</c>
			</c>
		</row>
	</rowsItem>
	<rowsItem>
		<index>6</index>
		<row>
			<formatIndex>18</formatIndex>
			<c>
				<c>
					<f>19</f>
				</c>
			</c>
			<c>
				<c>
					<f>20</f>
				</c>
			</c>
			<c>
				<c>
					<f>20</f>
				</c>
			</c>
			<c>
				<c>
					<f>20</f>
				</c>
			</c>
			<c>
				<c>
					<f>20</f>
				</c>
			</c>
			<c>
				<c>
					<f>21</f>
				</c>
			</c>
		</row>
	</rowsItem>
	<rowsItem>
		<index>9</index>
		<row>
			<c>
				<i>1</i>
				<c>
					<f>22</f>
					<tl>
						<v8:item>
							<v8:lang>ru</v8:lang>
							<v8:content>Перечень ветеринарных свидетельств к накладной [Номер] от [Дата]</v8:content>
						</v8:item>
					</tl>
				</c>
			</c>
		</row>
	</rowsItem>
	<drawing>
		<drawingType>Picture</drawingType>
		<id>1</id>
		<formatIndex>23</formatIndex>
		<beginRow>0</beginRow>
		<beginRowOffset>18</beginRowOffset>
		<endRow>6</endRow>
		<endRowOffset>39</endRowOffset>
		<beginColumn>3</beginColumn>
		<beginColumnOffset>33</beginColumnOffset>
		<endColumn>5</endColumn>
		<endColumnOffset>102</endColumnOffset>
		<autoSize>false</autoSize>
		<pictureSize>Proportionally</pictureSize>
		<zOrder>0</zOrder>
		<pictureIndex>1</pictureIndex>
	</drawing>
	<picture>
		<index>0</index>
		<picture t="false">iVBORw0KGgoAAAANSUhEUgAAAJoAAACaAQAAAAB5hGy6AAADVUlEQVR4Ac2VwYpm
OQiFBbcBXyXgVvDVBbeCrxJwG8hYt7thYJJez4WqUN9f+W88OR7h/Pex/yUEBKQ1
S6BY95ygL6g1NGKDmKeB1nnCyaC059AF5oSFf4HMUdvGqVGh/DdIPmDsPhrrwb9A
rSSzPhfRzFN/znmBgPzv50/tF3iOnFyOChTbVH/reYHh6LgGA+RQT/+232GUbVwl
wcY1935Cgt7Uitl0NUHO84J9E7B+tEjjLGXSFzxItkBhjzJAETwv6CqFo1BCvIB4
6AtCjR0YY8nwZhRPKNJSdIH7BHehwucF1UJ2qytxlLPXJxQNVB8SZKhJkvqCCEst
Y4L16n0r5wVTW76hwEQaqvjZ5gp39SuE8mimUa/nBU/ONXXCLl4Mc9YTRrtfMXFq
KmmK6gviAZ07wbRdQfZL5CvsP1eXKT57nf5LkCvEH58MLAoaP52l5wX7OKNN6Ckp
TeDbfoW0WdNOe8Y5rD84L5htv66vq+Pu8hblCUFcY6cGhWS4fi+6wpoCs7dOmzKX
ynf4K9yCWMXAI9NzrPVd8RUCz+IKEO37Y8AnHDqwVXDF1sNEx3nBw3K0c4rJEqLP
pi84FdHSjwpXbfy1/QoNZszqKB8hNEbHwQtCVlc50Wu5FvcXvSBbsTfPWv1TTE8Y
hISIeVBOr+e7jivEGbt722H/Xs8Lav4MqZW8cHCtUU84Z4wYNIJmV8njC6sr5J54
LcihLniecb6gvsJa+yzbe+faJqtVeUGUSRt3isiYY8V+Qm3d+spat/7tffwn5Laq
GK3WYyuJfBF0hcM69Eixd1pNc3/C1OrUb6+2yT381BMOd8sVmexOm+ozwxUSuXtf
bQ+ScoTAJ9ydOiDdBN1d3eTre9EVdgNMLl3YZmxd0J5QbY0xu2VW21yE5hNiB/Cw
cWZtgtK+5hf0KbY7XmwT7W6x9YZUu0OiS2CgnPrZ5goZVsbPrOBVURVfrF2hdmBE
KOHMPvuKX2XeoExdjt3aSnvAAHrCn2TJ6vGIa7clOwFfENCDc1CP5rWk+Bu7V6iF
K723C9iOUn3Cyc21M1gpfwLgi6AHZJJp2tO3Q7P/47xhmEOBT7fTWelP2FGmZoXe
4z7K82uZKwQM3HHaChEcUd8ov8L/Pv9H+A/LesO1T9MBYgAAAABJRU5ErkJggg==
</picture>
	</picture>
	<templateMode>true</templateMode>
	<defaultFormatIndex>24</defaultFormatIndex>
	<height>11</height>
	<vgRows>11</vgRows>
	<merge>
		<r>9</r>
		<c>1</c>
		<w>4</w>
	</merge>
	<namedItem xsi:type="NamedItemCells">
		<name>ВСДСтрока</name>
		<area>
			<type>Rows</type>
			<beginRow>0</beginRow>
			<endRow>6</endRow>
			<beginColumn>-1</beginColumn>
			<endColumn>-1</endColumn>
		</area>
	</namedItem>
	<namedItem xsi:type="NamedItemDrawing">
		<name>КартинкаQRКода</name>
		<drawingID>1</drawingID>
	</namedItem>
	<namedItem xsi:type="NamedItemCells">
		<name>Шапка</name>
		<area>
			<type>Rows</type>
			<beginRow>8</beginRow>
			<endRow>10</endRow>
			<beginColumn>-1</beginColumn>
			<endColumn>-1</endColumn>
		</area>
	</namedItem>
	<line width="1" gap="false">
		<v8ui:style xsi:type="v8ui:SpreadsheetDocumentCellLineType">Solid</v8ui:style>
	</line>
	<line width="1" gap="false">
		<v8ui:style xsi:type="v8ui:SpreadsheetDocumentDrawingLineType">None</v8ui:style>
	</line>
	<font faceName="Arial" height="14" bold="true" italic="false" underline="false" strikeout="false" kind="Absolute"/>
	<font faceName="Arial" height="14" bold="false" italic="false" underline="false" strikeout="false" kind="Absolute"/>
	<font faceName="Arial" height="12" bold="true" italic="false" underline="false" strikeout="false" kind="Absolute"/>
	<font faceName="Arial" height="12" bold="false" italic="false" underline="false" strikeout="false" kind="Absolute"/>
	<font faceName="Arial" height="16" bold="true" italic="false" underline="false" strikeout="false" kind="Absolute"/>
	<format>
		<width>23</width>
	</format>
	<format>
		<width>239</width>
	</format>
	<format>
		<width>517</width>
	</format>
	<format>
		<width>61</width>
	</format>
	<format>
		<leftBorder>0</leftBorder>
		<topBorder>0</topBorder>
	</format>
	<format>
		<topBorder>0</topBorder>
	</format>
	<format>
		<topBorder>0</topBorder>
		<rightBorder>0</rightBorder>
	</format>
	<format>
		<leftBorder>0</leftBorder>
	</format>
	<format>
		<font>0</font>
		<bottomBorder>0</bottomBorder>
		<width>149</width>
	</format>
	<format>
		<font>1</font>
		<bottomBorder>0</bottomBorder>
		<textPlacement>Cut</textPlacement>
		<fillType>Parameter</fillType>
	</format>
	<format>
		<rightBorder>0</rightBorder>
	</format>
	<format>
		<font>2</font>
		<bottomBorder>0</bottomBorder>
		<width>149</width>
	</format>
	<format>
		<font>3</font>
		<bottomBorder>0</bottomBorder>
		<textPlacement>Cut</textPlacement>
		<fillType>Parameter</fillType>
	</format>
	<format>
		<font>2</font>
		<bottomBorder>0</bottomBorder>
	</format>
	<format>
		<font>3</font>
		<bottomBorder>0</bottomBorder>
		<textPlacement>Cut</textPlacement>
		<fillType>Parameter</fillType>
		<format>
			<v8:item>
				<v8:lang>ru</v8:lang>
				<v8:content>ДФ=dd.MM.yyyy</v8:content>
			</v8:item>
		</format>
	</format>
	<format>
		<font>0</font>
		<bottomBorder>0</bottomBorder>
	</format>
	<format>
		<font>0</font>
		<bottomBorder>0</bottomBorder>
		<fillType>Parameter</fillType>
	</format>
	<format>
		<height>63</height>
	</format>
	<format>
		<leftBorder>0</leftBorder>
		<bottomBorder>0</bottomBorder>
	</format>
	<format>
		<bottomBorder>0</bottomBorder>
	</format>
	<format>
		<rightBorder>0</rightBorder>
		<bottomBorder>0</bottomBorder>
	</format>
	<format>
		<font>4</font>
		<horizontalAlignment>Center</horizontalAlignment>
		<fillType>Template</fillType>
	</format>
	<format>
		<drawingBorder>1</drawingBorder>
	</format>
	<format>
		<width>72</width>
	</format>
</document>