<?xml version="1.0" encoding="UTF-8"?>
<MetaDataObject xmlns="http://v8.1c.ru/8.3/MDClasses" xmlns:app="http://v8.1c.ru/8.2/managed-application/core" xmlns:cfg="http://v8.1c.ru/8.1/data/enterprise/current-config" xmlns:cmi="http://v8.1c.ru/8.2/managed-application/cmi" xmlns:ent="http://v8.1c.ru/8.1/data/enterprise" xmlns:lf="http://v8.1c.ru/8.2/managed-application/logform" xmlns:style="http://v8.1c.ru/8.1/data/ui/style" xmlns:sys="http://v8.1c.ru/8.1/data/ui/fonts/system" xmlns:v8="http://v8.1c.ru/8.1/data/core" xmlns:v8ui="http://v8.1c.ru/8.1/data/ui" xmlns:web="http://v8.1c.ru/8.1/data/ui/colors/web" xmlns:win="http://v8.1c.ru/8.1/data/ui/colors/windows" xmlns:xen="http://v8.1c.ru/8.3/xcf/enums" xmlns:xpr="http://v8.1c.ru/8.3/xcf/predef" xmlns:xr="http://v8.1c.ru/8.3/xcf/readable" xmlns:xs="http://www.w3.org/2001/XMLSchema" xmlns:xsi="http://www.w3.org/2001/XMLSchema-instance" version="2.4">
	<CommonCommand uuid="cb29d5c3-f947-479c-9295-cdd539c37aa3">
		<Properties>
			<Name>СвойстваИКатегории</Name>
			<Synonym>
				<v8:item>
					<v8:lang>ru</v8:lang>
					<v8:content>Свойства и категории</v8:content>
				</v8:item>
			</Synonym>
			<Comment/>
			<Group>FormNavigationPanelGoTo</Group>
			<Representation>Auto</Representation>
			<ToolTip/>
			<Picture/>
			<Shortcut/>
			<IncludeHelpInContents>false</IncludeHelpInContents>
			<CommandParameterType>
				<v8:Type>cfg:DocumentRef.ОтчетКомитентуОПродажах</v8:Type>
				<v8:Type>cfg:DocumentRef.ОприходованиеТоваров</v8:Type>
				<v8:Type>cfg:DocumentRef.ЗакрытиеПланируемыхПоступленийДенежныхСредств</v8:Type>
				<v8:Type>cfg:DocumentRef.РегистрацияРазовыхУдержанийРаботниковОрганизаций</v8:Type>
				<v8:Type>cfg:DocumentRef.ВводКоэффициентовИндексацииЗаработка</v8:Type>
				<v8:Type>cfg:DocumentRef.ЗакрытиеГода</v8:Type>
				<v8:Type>cfg:DocumentRef.ОтражениеПоступленияТоваровИУслугНДС</v8:Type>
				<v8:Type>cfg:DocumentRef.ВыгрузкаРегламентированныхОтчетов</v8:Type>
				<v8:Type>cfg:DocumentRef.ОтчетОСоставеСмены</v8:Type>
				<v8:Type>cfg:DocumentRef.ЗаявкаНаОбучение</v8:Type>
				<v8:Type>cfg:DocumentRef.УстановкаПорядкаЗакрытияПодразделений</v8:Type>
				<v8:Type>cfg:DocumentRef.АктОбОказанииПроизводственныхУслуг</v8:Type>
				<v8:Type>cfg:DocumentRef.ОтражениеРеализацииТоваровИУслугНДС</v8:Type>
				<v8:Type>cfg:DocumentRef.ПринятиеКУчетуНМА</v8:Type>
				<v8:Type>cfg:DocumentRef.НачислениеЕдиновременныхПособийЗаСчетФСС</v8:Type>
				<v8:Type>cfg:DocumentRef.ИзменениеСпособовОтраженияРасходовПоАмортизацииОС</v8:Type>
				<v8:Type>cfg:DocumentRef.ТранспортноеСообщение</v8:Type>
				<v8:Type>cfg:DocumentRef.ПоступлениеНМАМеждународный</v8:Type>
				<v8:Type>cfg:DocumentRef.ПланированиеОбучения</v8:Type>
				<v8:Type>cfg:CatalogRef.НоменклатурныеГруппы</v8:Type>
				<v8:Type>cfg:DocumentRef.ПереоценкаТоваровВРознице</v8:Type>
				<v8:Type>cfg:DocumentRef.ВосстановлениеНДСпоОбъектамНедвижимости</v8:Type>
				<v8:Type>cfg:DocumentRef.СчетНаОплатуПоставщика</v8:Type>
				<v8:Type>cfg:DocumentRef.ИсполнительныйЛист</v8:Type>
				<v8:Type>cfg:DocumentRef.РасчетПоМоделиБюджетирования</v8:Type>
				<v8:Type>cfg:DocumentRef.НачислениеДивидендовОрганизаций</v8:Type>
				<v8:Type>cfg:DocumentRef.ОплатаПоСреднемуЗаработку</v8:Type>
				<v8:Type>cfg:DocumentRef.ЧекККМ</v8:Type>
				<v8:Type>cfg:DocumentRef.РеестрДСВ3</v8:Type>
				<v8:Type>cfg:DocumentRef.ВводСведенийОПлановыхНачисленияхРаботниковОрганизаций</v8:Type>
				<v8:Type>cfg:DocumentRef.ВнутреннееПеремещениеСредствПриБюджетировании</v8:Type>
				<v8:Type>cfg:DocumentRef.ВводНачальныхОстатковНДС</v8:Type>
				<v8:Type>cfg:DocumentRef.УстановкаСоответствияСчетовБУиНУ</v8:Type>
				<v8:Type>cfg:DocumentRef.ПереносПроводокМеждународный</v8:Type>
				<v8:Type>cfg:DocumentRef.ЗакрытиеЗаказовНаПроизводство</v8:Type>
				<v8:Type>cfg:DocumentRef.НачислениеЗарплатыРаботникам</v8:Type>
				<v8:Type>cfg:DocumentRef.ОбесценениеАктивовМеждународный</v8:Type>
				<v8:Type>cfg:DocumentRef.ОплатаОтПокупателяПлатежнойКартой</v8:Type>
				<v8:Type>cfg:CatalogRef.ПрофилиПолномочийПользователей</v8:Type>
				<v8:Type>cfg:DocumentRef.ВыдачаДенежныхДокументов</v8:Type>
				<v8:Type>cfg:DocumentRef.РегламентированныйОтчет</v8:Type>
				<v8:Type>cfg:DocumentRef.ИзменениеЛимитовОтпускаМатериалов</v8:Type>
				<v8:Type>cfg:DocumentRef.КадровоеПеремещениеОрганизаций</v8:Type>
				<v8:Type>cfg:DocumentRef.ИнвентаризацияНЗП</v8:Type>
				<v8:Type>cfg:CatalogRef.ПодразделенияОрганизаций</v8:Type>
				<v8:Type>cfg:DocumentRef.ОплатаСверхурочныхЧасов</v8:Type>
				<v8:Type>cfg:DocumentRef.ОтражениеВУчетеБухгалтерскихРасчетовСПерсоналом</v8:Type>
				<v8:Type>cfg:DocumentRef.УстановкаБазыРаспределенияЗатрат</v8:Type>
				<v8:Type>cfg:DocumentRef.ПриемНаРаботуВОрганизацию</v8:Type>
				<v8:Type>cfg:DocumentRef.ПереоценкаВалютныхСтатейПриБюджетировании</v8:Type>
				<v8:Type>cfg:DocumentRef.ИзменениеПараметровНМАМеждународный</v8:Type>
				<v8:Type>cfg:DocumentRef.ОценкаНезавершенногоПроизводства</v8:Type>
				<v8:Type>cfg:DocumentRef.КадровоеПеремещение</v8:Type>
				<v8:Type>cfg:DocumentRef.РаспределениеНДСКосвенныхРасходов</v8:Type>
				<v8:Type>cfg:DocumentRef.УстановкаЦенНоменклатуры</v8:Type>
				<v8:Type>cfg:DocumentRef.ЗаявкаНаСертификациюНоменклатуры</v8:Type>
				<v8:Type>cfg:DocumentRef.УстановкаЗависимостейОборотовПоСтатьям</v8:Type>
				<v8:Type>cfg:DocumentRef.РегистрацияОплатыНДСВБюджет</v8:Type>
				<v8:Type>cfg:DocumentRef.НеформализованныйДокументНалоговогоОргана</v8:Type>
				<v8:Type>cfg:DocumentRef.ВозвратТоваровПоставщикуИзНТТ</v8:Type>
				<v8:Type>cfg:CatalogRef.ДолжностиОрганизаций</v8:Type>
				<v8:Type>cfg:DocumentRef.АттестацияРаботника</v8:Type>
				<v8:Type>cfg:DocumentRef.Увольнение</v8:Type>
				<v8:Type>cfg:DocumentRef.ТребованиеНакладная</v8:Type>
				<v8:Type>cfg:DocumentRef.ОтчетОРозничныхПродажах</v8:Type>
				<v8:Type>cfg:DocumentRef.ИзменениеСпециальногоКоэффициентаНМА</v8:Type>
				<v8:Type>cfg:DocumentRef.ВыработкаНМА</v8:Type>
				<v8:Type>cfg:DocumentRef.ПереводОсновныхСредствИИнвестиционнойСобственностиМеждународный</v8:Type>
				<v8:Type>cfg:CatalogRef.Проекты</v8:Type>
				<v8:Type>cfg:DocumentRef.ВводРаспределенияОсновногоЗаработкаРаботниковОрганизации</v8:Type>
				<v8:Type>cfg:DocumentRef.ЗакрытиеВнутреннихЗаказов</v8:Type>
				<v8:Type>cfg:DocumentRef.АктОтбораПробНоменклатуры</v8:Type>
				<v8:Type>cfg:DocumentRef.НачислениеПоБольничномуЛисту</v8:Type>
				<v8:Type>cfg:CatalogRef.КонтактныеЛица</v8:Type>
				<v8:Type>cfg:DocumentRef.КорректировкаСтоимостиСписанияТоваров</v8:Type>
				<v8:Type>cfg:DocumentRef.АккредитивПолученный</v8:Type>
				<v8:Type>cfg:DocumentRef.КомплектацияОС</v8:Type>
				<v8:Type>cfg:CatalogRef.ФизическиеЛица</v8:Type>
				<v8:Type>cfg:DocumentRef.ПереносПартийМеждународный</v8:Type>
				<v8:Type>cfg:DocumentRef.Сторнирование</v8:Type>
				<v8:Type>cfg:DocumentRef.ПереоценкаВалютныхСредств</v8:Type>
				<v8:Type>cfg:DocumentRef.ОтчетПроизводстваЗаСмену</v8:Type>
				<v8:Type>cfg:DocumentRef.ВводСведенийОРеглУчетеПлановыхНачисленийРаботниковОрганизаций</v8:Type>
				<v8:Type>cfg:DocumentRef.РеализацияУслугПоПереработке</v8:Type>
				<v8:Type>cfg:DocumentRef.ВводНачальныхОстатковНДСпоПартиям</v8:Type>
				<v8:Type>cfg:DocumentRef.УчетПоложенийПереходногоПериодаПоНДС</v8:Type>
				<v8:Type>cfg:DocumentRef.ЗарплатаКВыплате</v8:Type>
				<v8:Type>cfg:DocumentRef.ЗакрытиеЗаявокНаРасходованиеСредств</v8:Type>
				<v8:Type>cfg:DocumentRef.ПогашениеЗадолженностиПодотчетныхЛицВРегламентированномУчете</v8:Type>
				<v8:Type>cfg:DocumentRef.СчетФактураПолученный</v8:Type>
				<v8:Type>cfg:DocumentRef.ИнвентаризацияОС</v8:Type>
				<v8:Type>cfg:DocumentRef.ИзменениеПараметровНачисленияАмортизацииОС</v8:Type>
				<v8:Type>cfg:DocumentRef.ЗапросНаИнформационноеОбслуживаниеНалогоплательщика</v8:Type>
				<v8:Type>cfg:DocumentRef.ВосстановлениеНДС</v8:Type>
				<v8:Type>cfg:DocumentRef.СписаниеНДС</v8:Type>
				<v8:Type>cfg:DocumentRef.ПоступлениеОсновныхСредствМеждународный</v8:Type>
				<v8:Type>cfg:DocumentRef.УдалитьОтсутствиеНаРаботе</v8:Type>
				<v8:Type>cfg:CatalogRef.ОсновныеСредства</v8:Type>
				<v8:Type>cfg:CatalogRef.НематериальныеАктивы</v8:Type>
				<v8:Type>cfg:DocumentRef.ОтменаСкидокНоменклатуры</v8:Type>
				<v8:Type>cfg:DocumentRef.ЗаданиеНаПроизводство</v8:Type>
				<v8:Type>cfg:DocumentRef.ABCКлассификацияПокупателей</v8:Type>
				<v8:Type>cfg:DocumentRef.УсловияПоставокПоДоговорамКонтрагентов</v8:Type>
				<v8:Type>cfg:DocumentRef.ПлатежноеПоручениеВходящее</v8:Type>
				<v8:Type>cfg:DocumentRef.ИнвентаризацияБракаВПроизводстве</v8:Type>
				<v8:Type>cfg:DocumentRef.ВозвратМатериаловИзЭксплуатации</v8:Type>
				<v8:Type>cfg:DocumentRef.НДФЛВозвратНалога</v8:Type>
				<v8:Type>cfg:DocumentRef.ДоговорНаВыполнениеРаботСФизЛицом</v8:Type>
				<v8:Type>cfg:DocumentRef.ВыработкаОС</v8:Type>
				<v8:Type>cfg:DocumentRef.СписаниеДепонентовВДоходыОрганизаций</v8:Type>
				<v8:Type>cfg:DocumentRef.РасчетНДСпоПродукции</v8:Type>
				<v8:Type>cfg:DocumentRef.ПоступлениеДенежныхДокументов</v8:Type>
				<v8:Type>cfg:DocumentRef.ЗаказНаПроизводство</v8:Type>
				<v8:Type>cfg:DocumentRef.ПереоценкаТоваровОтданныхНаКомиссию</v8:Type>
				<v8:Type>cfg:DocumentRef.РасчетЕСН</v8:Type>
				<v8:Type>cfg:DocumentRef.ИзменениеГрафиковАмортизацииОС</v8:Type>
				<v8:Type>cfg:DocumentRef.УстановкаПороговНакопительныхСкидок</v8:Type>
				<v8:Type>cfg:DocumentRef.ЗарплатаКВыплатеОрганизаций</v8:Type>
				<v8:Type>cfg:DocumentRef.ПередачаТоваров</v8:Type>
				<v8:Type>cfg:DocumentRef.ОтсутствияНаРабочемМесте</v8:Type>
				<v8:Type>cfg:DocumentRef.ИнвентаризацияТоваровНаСкладе</v8:Type>
				<v8:Type>cfg:DocumentRef.СчетФактураВыданный</v8:Type>
				<v8:Type>cfg:DocumentRef.ДокументРасчетовСКонтрагентом</v8:Type>
				<v8:Type>cfg:DocumentRef.СписаниеНЗП</v8:Type>
				<v8:Type>cfg:DocumentRef.КонтролируемыеЗначенияПоБюджетам</v8:Type>
				<v8:Type>cfg:DocumentRef.ВозвратТоваровПоставщику</v8:Type>
				<v8:Type>cfg:DocumentRef.ПланДвиженияДенежныхСредств</v8:Type>
				<v8:Type>cfg:DocumentRef.РезервированиеПомещений</v8:Type>
				<v8:Type>cfg:DocumentRef.УслугиСобственнымПодразделениям</v8:Type>
				<v8:Type>cfg:DocumentRef.ЗаявлениеОбОбменеДубликатеСтраховогоСвидетельства</v8:Type>
				<v8:Type>cfg:DocumentRef.ЗаписьКУДиР</v8:Type>
				<v8:Type>cfg:DocumentRef.ОтчетМастераСмены</v8:Type>
				<v8:Type>cfg:DocumentRef.ЗаказПоставщику</v8:Type>
				<v8:Type>cfg:DocumentRef.УстановкаТиповЦенПоГруппамНоменклатурыДляПокупателей</v8:Type>
				<v8:Type>cfg:DocumentRef.РасходыНаДобровольноеСтрахование</v8:Type>
				<v8:Type>cfg:DocumentRef.СписаниеНМА</v8:Type>
				<v8:Type>cfg:DocumentRef.ИнвентаризацияРасчетовСконтрагентами</v8:Type>
				<v8:Type>cfg:DocumentRef.ПеремещениеМатериаловВЭксплуатации</v8:Type>
				<v8:Type>cfg:DocumentRef.КорректировкаДолга</v8:Type>
				<v8:Type>cfg:DocumentRef.ДепонированиеОрганизаций</v8:Type>
				<v8:Type>cfg:DocumentRef.ПлатежноеТребованиеПолученное</v8:Type>
				<v8:Type>cfg:DocumentRef.НевыходыВОрганизациях</v8:Type>
				<v8:Type>cfg:DocumentRef.ПоступлениеДопРасходов</v8:Type>
				<v8:Type>cfg:DocumentRef.РасходныйКассовыйОрдер</v8:Type>
				<v8:Type>cfg:DocumentRef.ВводНачальныхОстатковОС</v8:Type>
				<v8:Type>cfg:DocumentRef.АккредитивПереданный</v8:Type>
				<v8:Type>cfg:DocumentRef.МодернизацияОС</v8:Type>
				<v8:Type>cfg:DocumentRef.РеализацияТоваровУслуг</v8:Type>
				<v8:Type>cfg:DocumentRef.СписаниеМатериаловИзЭксплуатации</v8:Type>
				<v8:Type>cfg:DocumentRef.КорректировкаЗаказаПоставщику</v8:Type>
				<v8:Type>cfg:DocumentRef.СдельныйНаряд</v8:Type>
				<v8:Type>cfg:DocumentRef.ОперацияБух</v8:Type>
				<v8:Type>cfg:DocumentRef.УвольнениеИзОрганизаций</v8:Type>
				<v8:Type>cfg:DocumentRef.РасчетСебестоимостиВыпуска</v8:Type>
				<v8:Type>cfg:DocumentRef.ВыборНоменклатурыДляНДС</v8:Type>
				<v8:Type>cfg:DocumentRef.РегламентныеОперацииНалоговогоУчетаПоУСН</v8:Type>
				<v8:Type>cfg:DocumentRef.ПрочиеЗатраты</v8:Type>
				<v8:Type>cfg:DocumentRef.УчетОсновногоЗаработкаРаботниковОрганизацииВРегламентированномУчете</v8:Type>
				<v8:Type>cfg:DocumentRef.ПоступлениеТоваровУслугВНТТ</v8:Type>
				<v8:Type>cfg:DocumentRef.ПриходныйОрдерНаТовары</v8:Type>
				<v8:Type>cfg:DocumentRef.ЗаказПокупателя</v8:Type>
				<v8:Type>cfg:DocumentRef.КорректировкаЗаказаПокупателя</v8:Type>
				<v8:Type>cfg:CatalogRef.КонтактныеЛицаКонтрагентов</v8:Type>
				<v8:Type>cfg:DocumentRef.ФормированиеПотребностей</v8:Type>
				<v8:Type>cfg:DocumentRef.УстановкаСкидокНоменклатуры</v8:Type>
				<v8:Type>cfg:DocumentRef.СведенияОТрудовомСтажеИЗаработкеСЗВ4</v8:Type>
				<v8:Type>cfg:DocumentRef.ВозвратПереданныхТоваров</v8:Type>
				<v8:Type>cfg:CatalogRef.Подразделения</v8:Type>
				<v8:Type>cfg:DocumentRef.ОприходованиеНЗП</v8:Type>
				<v8:Type>cfg:DocumentRef.АмортизацияНМАМеждународный</v8:Type>
				<v8:Type>cfg:DocumentRef.ИзменениеСпециальногоКоэффициентаОС</v8:Type>
				<v8:Type>cfg:DocumentRef.РазмещениеЗаказа</v8:Type>
				<v8:Type>cfg:DocumentRef.ВводРаспределенияЗаработкаРаботников</v8:Type>
				<v8:Type>cfg:DocumentRef.КорректировкаДолгаПоВозвратнойТаре</v8:Type>
				<v8:Type>cfg:DocumentRef.ПередачаМатериаловВЭксплуатацию</v8:Type>
				<v8:Type>cfg:DocumentRef.РасчетПлановойСебестоимостиПродукции</v8:Type>
				<v8:Type>cfg:DocumentRef.ДенежныйЧек</v8:Type>
				<v8:Type>cfg:DocumentRef.НачислениеОтпускаРаботникамОрганизаций</v8:Type>
				<v8:Type>cfg:DocumentRef.ОплатаПраздничныхИВыходныхДнейОрганизаций</v8:Type>
				<v8:Type>cfg:DocumentRef.ПоступлениеТоваровУслуг</v8:Type>
				<v8:Type>cfg:DocumentRef.ПремииРаботниковОрганизаций</v8:Type>
				<v8:Type>cfg:DocumentRef.ВозвратНаРаботуОрганизаций</v8:Type>
				<v8:Type>cfg:DocumentRef.ИзменениеЗаказаПокупателя</v8:Type>
				<v8:Type>cfg:DocumentRef.ПодтверждениеНулевойСтавкиНДС</v8:Type>
				<v8:Type>cfg:DocumentRef.КорректировкаПоступления</v8:Type>
				<v8:Type>cfg:DocumentRef.ПоступлениеНМА</v8:Type>
				<v8:Type>cfg:DocumentRef.ПередачаОборудованияВМонтаж</v8:Type>
				<v8:Type>cfg:DocumentRef.Встречи</v8:Type>
				<v8:Type>cfg:DocumentRef.ИнвентаризацияТоваровОтданныхНаКомиссию</v8:Type>
				<v8:Type>cfg:DocumentRef.УчастиеВМероприятиях</v8:Type>
				<v8:Type>cfg:DocumentRef.ТабельУчетаРабочегоВремениОрганизации</v8:Type>
				<v8:Type>cfg:DocumentRef.КлассификацияПокупателейПоСтадиямВзаимоотношений</v8:Type>
				<v8:Type>cfg:DocumentRef.ВнутреннийЗаказ</v8:Type>
				<v8:Type>cfg:DocumentRef.ВводИнформацииОСотрудниках</v8:Type>
				<v8:Type>cfg:DocumentRef.ГрафикОтпусковОрганизаций</v8:Type>
				<v8:Type>cfg:DocumentRef.ИзменениеСостоянияОС</v8:Type>
				<v8:Type>cfg:DocumentRef.СписаниеОС</v8:Type>
				<v8:Type>cfg:DocumentRef.ЗакрытиеСчетовГодаМеждународный</v8:Type>
				<v8:Type>cfg:DocumentRef.ПередачаОС</v8:Type>
				<v8:Type>cfg:DocumentRef.РегистрацияРазовыхНачисленийРаботниковОрганизаций</v8:Type>
				<v8:Type>cfg:DocumentRef.ДоговорЗаймаСРаботником</v8:Type>
				<v8:Type>cfg:CatalogRef.Контрагенты</v8:Type>
				<v8:Type>cfg:DocumentRef.ВводНачальныхОстатковУСН</v8:Type>
				<v8:Type>cfg:DocumentRef.АктуализацияБюджетов</v8:Type>
				<v8:Type>cfg:DocumentRef.УстановкаЦенНоменклатурыКонтрагентов</v8:Type>
				<v8:Type>cfg:DocumentRef.ПриходныйКассовыйОрдер</v8:Type>
				<v8:Type>cfg:DocumentRef.АнкетаЗастрахованногоЛица</v8:Type>
				<v8:Type>cfg:DocumentRef.НДФЛПодтверждениеПраваНаИмущественныйВычет</v8:Type>
				<v8:Type>cfg:DocumentRef.ЗаявкаНаОткрытиеСчетов</v8:Type>
				<v8:Type>cfg:DocumentRef.ИзменениеЛимитовВозвратнойТары</v8:Type>
				<v8:Type>cfg:DocumentRef.ПогашениеСтоимости</v8:Type>
				<v8:Type>cfg:DocumentRef.ПлатежныйОрдерСписаниеДенежныхСредств</v8:Type>
				<v8:Type>cfg:DocumentRef.ВводСведенийОПлановыхУдержанияхРаботниковОрганизаций</v8:Type>
				<v8:Type>cfg:DocumentRef.ПереоценкаВалютныхСтатейМеждународный</v8:Type>
				<v8:Type>cfg:DocumentRef.ИнкассовоеПоручениеПолученное</v8:Type>
				<v8:Type>cfg:DocumentRef.КорректировкаЗаписейРегистров</v8:Type>
				<v8:Type>cfg:DocumentRef.ПогашениеЗадолженностиПодотчетныхЛиц</v8:Type>
				<v8:Type>cfg:DocumentRef.СписаниеМПЗМеждународный</v8:Type>
				<v8:Type>cfg:DocumentRef.КорректировкаОстатковПоПрогнознымБалансам</v8:Type>
				<v8:Type>cfg:DocumentRef.СписаниеРасходовБудущихПериодов</v8:Type>
				<v8:Type>cfg:DocumentRef.РеализацияОтгруженныхТоваров</v8:Type>
				<v8:Type>cfg:DocumentRef.НДФЛиЕСНДоходыИНалоги</v8:Type>
				<v8:Type>cfg:DocumentRef.РасчетПриУвольненииРаботникаОрганизаций</v8:Type>
				<v8:Type>cfg:DocumentRef.УстановкаНаценокПоУсловиямПродаж</v8:Type>
				<v8:Type>cfg:DocumentRef.ПодготовкаКПередачеОС</v8:Type>
				<v8:Type>cfg:DocumentRef.НачислениеНДСпоСМРхозспособом</v8:Type>
				<v8:Type>cfg:DocumentRef.РегистрацияПростоевРаботниковОрганизаций</v8:Type>
				<v8:Type>cfg:DocumentRef.ОперацияМеждународная</v8:Type>
				<v8:Type>cfg:DocumentRef.СчетНаОплатуПокупателю</v8:Type>
				<v8:Type>cfg:DocumentRef.ОбъявлениеНаВзносНаличными</v8:Type>
				<v8:Type>cfg:DocumentRef.ВозвратТоваровОтПокупателя</v8:Type>
				<v8:Type>cfg:DocumentRef.ПеремещениеТоваров</v8:Type>
				<v8:Type>cfg:DocumentRef.ВводСведенийОПлановыхНачисленияхУдержанияхРаботников</v8:Type>
				<v8:Type>cfg:DocumentRef.РезультатИспытательногоСрока</v8:Type>
				<v8:Type>cfg:CatalogRef.Организации</v8:Type>
				<v8:Type>cfg:DocumentRef.ФормированиеЗаписейКнигиПродаж</v8:Type>
				<v8:Type>cfg:DocumentRef.ФормированиеЗаписейКнигиПокупок</v8:Type>
				<v8:Type>cfg:DocumentRef.НеформализованныйДокументНалогоплательщика</v8:Type>
				<v8:Type>cfg:DocumentRef.КомандировкиОрганизаций</v8:Type>
				<v8:Type>cfg:DocumentRef.ПереносЗатратНаПроизводствоМеждународный</v8:Type>
				<v8:Type>cfg:DocumentRef.НачислениеРезервовМеждународный</v8:Type>
				<v8:Type>cfg:DocumentRef.СертификацияНоменклатуры</v8:Type>
				<v8:Type>cfg:DocumentRef.РегистрацияОплатыОсновныхСредствДляУСН</v8:Type>
				<v8:Type>cfg:DocumentRef.Событие</v8:Type>
				<v8:Type>cfg:DocumentRef.НДФЛПерерасчет</v8:Type>
				<v8:Type>cfg:DocumentRef.УстановкаДиапазоновБазовыхЦен</v8:Type>
				<v8:Type>cfg:DocumentRef.РасходныйОрдерНаТовары</v8:Type>
				<v8:Type>cfg:DocumentRef.ВыпускПродукции</v8:Type>
				<v8:Type>cfg:DocumentRef.УчетЗаработкаРаботников</v8:Type>
				<v8:Type>cfg:DocumentRef.ОтчетКомиссионераОПродажах</v8:Type>
				<v8:Type>cfg:DocumentRef.ВыбытиеНМАМеждународный</v8:Type>
				<v8:Type>cfg:DocumentRef.ИзменениеПараметровОсновныхСредствМеждународный</v8:Type>
				<v8:Type>cfg:DocumentRef.ОпределениеФинансовыхРезультатов</v8:Type>
				<v8:Type>cfg:DocumentRef.ВнутреннееПеремещениеНаличныхДенежныхСредств</v8:Type>
				<v8:Type>cfg:DocumentRef.РассылкаАнкет</v8:Type>
				<v8:Type>cfg:DocumentRef.ПринятиеКУчетуОС</v8:Type>
				<v8:Type>cfg:DocumentRef.КорректировкаВнутреннегоЗаказа</v8:Type>
				<v8:Type>cfg:DocumentRef.ФиксацияБюджетов</v8:Type>
				<v8:Type>cfg:DocumentRef.ПлатежноеТребованиеВыставленное</v8:Type>
				<v8:Type>cfg:DocumentRef.ВводНачальныхОстатковПоВзаиморасчетам</v8:Type>
				<v8:Type>cfg:DocumentRef.ПоступлениеТоваровИзПереработки</v8:Type>
				<v8:Type>cfg:DocumentRef.ПрохождениеКурсаОбучения</v8:Type>
				<v8:Type>cfg:DocumentRef.ВнутреннееПеремещениеОсновныхСредствМеждународный</v8:Type>
				<v8:Type>cfg:DocumentRef.ОтражениеЗарплатыВУпрУчете</v8:Type>
				<v8:Type>cfg:DocumentRef.ПередачаСЗВ4вПФР</v8:Type>
				<v8:Type>cfg:DocumentRef.РасчетыПоНалогуНаПрибыль</v8:Type>
				<v8:Type>cfg:DocumentRef.ЗакрытиеЗаказовПоставщикам</v8:Type>
				<v8:Type>cfg:DocumentRef.ИзменениеСпособовОтраженияРасходовПоАмортизацииНМА</v8:Type>
				<v8:Type>cfg:DocumentRef.АмортизацияОСМеждународный</v8:Type>
				<v8:Type>cfg:DocumentRef.НачислениеРасходовМеждународный</v8:Type>
				<v8:Type>cfg:DocumentRef.ПлатежныйОрдерПоступлениеДенежныхСредств</v8:Type>
				<v8:Type>cfg:DocumentRef.КорректировкаРеализации</v8:Type>
				<v8:Type>cfg:DocumentRef.ЭлектронноеПисьмо</v8:Type>
				<v8:Type>cfg:DocumentRef.УдалитьВозвратНаРаботу</v8:Type>
				<v8:Type>cfg:DocumentRef.УчетФактическихДанныхПоБюджетам</v8:Type>
				<v8:Type>cfg:DocumentRef.УчетЗатратНаИсточникиПерсонала</v8:Type>
				<v8:Type>cfg:CatalogRef.ЛичныеКонтакты</v8:Type>
				<v8:Type>cfg:DocumentRef.ВводНачальныхОстатковМатериаловВЭксплуатации</v8:Type>
				<v8:Type>cfg:DocumentRef.СведенияОТрудовомСтажеЗастрахованногоЛицаСЗВК</v8:Type>
				<v8:Type>cfg:DocumentRef.РеестрСчетов</v8:Type>
				<v8:Type>cfg:DocumentRef.УстановкаСоответствияСчетовБУиМСФО</v8:Type>
				<v8:Type>cfg:DocumentRef.Опрос</v8:Type>
				<v8:Type>cfg:DocumentRef.ПлатежноеПоручениеИсходящее</v8:Type>
				<v8:Type>cfg:DocumentRef.ИзменениеУсловийОплатыОтпускаПоУходуЗаРебенком</v8:Type>
				<v8:Type>cfg:DocumentRef.ГТДИмпорт</v8:Type>
				<v8:Type>cfg:DocumentRef.ПередачаДСВвПФР</v8:Type>
				<v8:Type>cfg:DocumentRef.НачислениеЗарплатыРаботникамОрганизаций</v8:Type>
				<v8:Type>cfg:DocumentRef.ИзменениеКадровогоПлана</v8:Type>
				<v8:Type>cfg:CatalogRef.СотрудникиОрганизаций</v8:Type>
				<v8:Type>cfg:DocumentRef.ОтражениеЗарплатыВРеглУчете</v8:Type>
				<v8:Type>cfg:DocumentRef.ОприходованиеМатериаловИзПроизводства</v8:Type>
				<v8:Type>cfg:DocumentRef.ПриемНаРаботу</v8:Type>
				<v8:Type>cfg:DocumentRef.СведенияОДоходахФизлиц</v8:Type>
				<v8:Type>cfg:CatalogRef.Номенклатура</v8:Type>
				<v8:Type>cfg:DocumentRef.ОтпускПоУходуЗаРебенком</v8:Type>
				<v8:Type>cfg:DocumentRef.РаспределениеМатериаловНаВыпуск</v8:Type>
				<v8:Type>cfg:DocumentRef.РегламентныеОперацииНалоговогоУчетаПоНалогуНаПрибыль</v8:Type>
				<v8:Type>cfg:DocumentRef.ПеремещениеОС</v8:Type>
				<v8:Type>cfg:DocumentRef.РезервированиеТоваров</v8:Type>
				<v8:Type>cfg:DocumentRef.НеявкиИБолезниОрганизаций</v8:Type>
				<v8:Type>cfg:DocumentRef.ПланированиеОтпуска</v8:Type>
				<v8:Type>cfg:DocumentRef.ПереоценкаТоваровПринятыхНаКомиссию</v8:Type>
				<v8:Type>cfg:DocumentRef.КомплектацияНоменклатуры</v8:Type>
				<v8:Type>cfg:DocumentRef.КорректировкаКачестваТоваров</v8:Type>
				<v8:Type>cfg:DocumentRef.ПереносЗадолженностиРаботниковОрганизаций</v8:Type>
				<v8:Type>cfg:DocumentRef.КорректировкаСерийИХарактеристикТоваров</v8:Type>
				<v8:Type>cfg:DocumentRef.КорректировкаПрочихЗатрат</v8:Type>
				<v8:Type>cfg:DocumentRef.КорректировкаЗаказаНаПроизводство</v8:Type>
				<v8:Type>cfg:DocumentRef.АктСверкиВзаиморасчетов</v8:Type>
				<v8:Type>cfg:DocumentRef.ПередачаНМА</v8:Type>
				<v8:Type>cfg:DocumentRef.ВводИндивидуальныхГрафиковРаботыОрганизации</v8:Type>
				<v8:Type>cfg:DocumentRef.ПланируемоеПоступлениеДенежныхСредств</v8:Type>
				<v8:Type>cfg:DocumentRef.Доверенность</v8:Type>
				<v8:Type>cfg:DocumentRef.БюджетнаяОперация</v8:Type>
				<v8:Type>cfg:DocumentRef.КорректировкаНЗП</v8:Type>
				<v8:Type>cfg:DocumentRef.ПереоценкаАктивовМеждународный</v8:Type>
				<v8:Type>cfg:DocumentRef.АвансовыйОтчет</v8:Type>
				<v8:Type>cfg:DocumentRef.АмортизацияОС</v8:Type>
				<v8:Type>cfg:DocumentRef.СписаниеТоваров</v8:Type>
				<v8:Type>cfg:DocumentRef.ВыбытиеОсновныхСредствМеждународный</v8:Type>
				<v8:Type>cfg:DocumentRef.ЗакрытиеЗаказовПокупателей</v8:Type>
				<v8:Type>cfg:DocumentRef.РаспределениеПрочихЗатрат</v8:Type>
				<v8:Type>cfg:DocumentRef.ПолучениеУслугПоПереработке</v8:Type>
				<v8:Type>cfg:DocumentRef.УстановкаПараметровУчетаНоменклатуры</v8:Type>
				<v8:Type>cfg:CatalogRef.ДоговорыКонтрагентов</v8:Type>
				<v8:Type>cfg:DocumentRef.ВводПроцентаДеятельностиЕНВД</v8:Type>
				<v8:Type>cfg:CatalogRef.Склады</v8:Type>
				<v8:Type>cfg:DocumentRef.ЗаказНаОбслуживаниеОС</v8:Type>
				<v8:Type>cfg:DocumentRef.ОтпускаОрганизаций</v8:Type>
				<v8:Type>cfg:DocumentRef.АмортизацияНМА</v8:Type>
				<v8:Type>cfg:DocumentRef.УстановкаДолейРаспределенияПоПроектам</v8:Type>
				<v8:Type>cfg:DocumentRef.ПравоНаДополнительныеДниОтпуска</v8:Type>
				<v8:Type>cfg:DocumentRef.ИнкассовоеПоручениеПереданное</v8:Type>
			</CommandParameterType>
			<ParameterUseMode>Single</ParameterUseMode>
			<ModifiesData>false</ModifiesData>
		</Properties>
	</CommonCommand>
</MetaDataObject>